status/__init__.py
status/py.typed
statuses-0.5.2.dist-info/LICENSE
statuses-0.5.2.dist-info/METADATA
statuses-0.5.2.dist-info/WHEEL
statuses-0.5.2.dist-info/top_level.txt
statuses-0.5.2.dist-info/RECORD
