Metadata-Version: 2.1
Name: statuses
Version: 0.5.2
Summary: The `Status` class represents the status of some event.
Home-page: https://github.com/chrisdotcode/statuses
Author: chrisdotcode
Author-email: pypi+chris@code.sc
License: BSD 3-Clause License
Platform: UNKNOWN
